compile/CompileMib.py
compile/__init__.py
loader/GitLoader.py
loader/MibLoader.py
loader/__init__.py
loader/compile_and_load_mibs.py
loader/load_mibs.py
temporaryContainer/TempDir.py
temporaryContainer/__init__.py
mibplugin-0.0.2.dist-info/LICENSE.rst
mibplugin-0.0.2.dist-info/METADATA
mibplugin-0.0.2.dist-info/WHEEL
mibplugin-0.0.2.dist-info/top_level.txt
mibplugin-0.0.2.dist-info/RECORD
