Metadata-Version: 2.1
Name: mibplugin
Version: 0.0.2
Summary: Mib Compilation and Loading
Author: BurgundyWillow
Author-email: 
License: BSD 3-Clause License
Keywords: mib,snmp
Classifier: License :: OSI Approved :: BSD License
Classifier: Programming Language :: Python :: 3
Classifier: Programming Language :: Python :: 3.7
License-File: LICENSE.rst
Requires-Dist: requests
Requires-Dist: pysnmp-bw
Requires-Dist: GitPython
